llama_index/packs/diff_private_simple_dataset/__init__.py
llama_index/packs/diff_private_simple_dataset/base.py
llama_index/packs/diff_private_simple_dataset/events.py
llama_index/packs/diff_private_simple_dataset/privacy_mechanism.py
llama_index/packs/diff_private_simple_dataset/templates.py
llama_index_packs_diff_private_simple_dataset-0.4.1.dist-info/METADATA
llama_index_packs_diff_private_simple_dataset-0.4.1.dist-info/WHEEL
llama_index_packs_diff_private_simple_dataset-0.4.1.dist-info/licenses/LICENSE
llama_index_packs_diff_private_simple_dataset-0.4.1.dist-info/RECORD
