Metadata-Version: 2.4
Name: llama-index-packs-diff-private-simple-dataset
Version: 0.4.1
Summary: llama-index packs diff private simple dataset
Author-email: Andrei Fajardo <andrei@llamaindex.ai>, "Chi Ho (Alex) Cheung" <chiho00hk@hotmail.com>, Logan Markewich <logan@llamaindex.ai>
License-Expression: MIT
License-File: LICENSE
Requires-Python: <3.12,>=3.9
Requires-Dist: llama-index-core<0.15,>=0.13.0
Requires-Dist: llama-index-llms-openai<0.6,>=0.5.0
Requires-Dist: pandas
Requires-Dist: prv-accountant<0.3,>=0.2.0
